{"cameraMode":{"drawMode":0,"name":"Shaded","section":"Shading Mode"},"sceneLighting":true,"audioPlay":false,"sceneViewState":{"showFog":true,"showMaterialUpdate":false,"showSkybox":true,"showFlares":true,"showImageEffects":true,"showParticleSystems":true},"in2DMode":false,"pivot":{"x":5.898936748504639,"y":6.857019424438477,"z":24.266521453857423},"rotation":{"x":-0.05148857831954956,"y":-0.14811700582504273,"z":-0.03582662343978882,"w":-0.9869785904884338},"size":17.326541900634767,"orthographic":false}